ping3/__init__.py
ping3/__main__.py
ping3/command_line.py
ping3/enums.py
ping3/errors.py
ping3-5.1.3.dist-info/licenses/LICENSE
ping3-5.1.3.dist-info/METADATA
ping3-5.1.3.dist-info/WHEEL
ping3-5.1.3.dist-info/entry_points.txt
ping3-5.1.3.dist-info/top_level.txt
ping3-5.1.3.dist-info/RECORD
