Metadata-Version: 2.4
Name: ping3
Version: 5.1.3
Summary: A pure python3 version of ICMP ping implementation using raw socket.
Author-email: Kyan <kai@kyan001.com>
License-Expression: MIT
Project-URL: Homepage, https://github.com/kyan001/ping3
Project-URL: Changelog, https://github.com/kyan001/ping3/blob/master/CHANGELOG.md
Project-URL: Issue Tracker, https://github.com/kyan001/ping3/issues
Project-URL: Source Code, https://github.com/kyan001/ping3
Keywords: python3,ping,icmp,socket,tool
Classifier: Development Status :: 5 - Production/Stable
Classifier: Intended Audience :: Developers
Classifier: Intended Audience :: End Users/Desktop
Classifier: Topic :: System :: Networking
Classifier: Programming Language :: Python :: 3
Classifier: Programming Language :: Python :: 3 :: Only
Requires-Python: >=3.5
License-File: LICENSE
Provides-Extra: dev
Requires-Dist: build; extra == "dev"
Requires-Dist: twine; extra == "dev"
Dynamic: license-file
